pwclient/__init__.py
pwclient/api.py
pwclient/checks.py
pwclient/exceptions.py
pwclient/parser.py
pwclient/patches.py
pwclient/projects.py
pwclient/shell.py
pwclient/states.py
pwclient/utils.py
pwclient/xmlrpc.py
pwclient-2.8.0.dist-info/COPYING
pwclient-2.8.0.dist-info/METADATA
pwclient-2.8.0.dist-info/WHEEL
pwclient-2.8.0.dist-info/entry_points.txt
pwclient-2.8.0.dist-info/pbr.json
pwclient-2.8.0.dist-info/top_level.txt
pwclient-2.8.0.dist-info/RECORD
